ty_python_learning/__init__.py
ty_python_learning/day01_datatypes/__init__.py
ty_python_learning/day01_datatypes/p01_data_types.py
ty_python_learning/day01_datatypes/p02_strings.py
ty_python_learning/day01_datatypes/p03_lists.py
ty_python_learning/day01_datatypes/p04_tuple.py
ty_python_learning/day01_datatypes/p05_dicts.py
ty_python_learning/day01_datatypes/p06_sets.py
ty_python_learning/day01_datatypes/p07_comprehensions.py
ty_python_learning/day02_flow_controls/__init__.py
ty_python_learning/day02_flow_controls/p01_conditions.py
ty_python_learning/day02_flow_controls/p02_loops.py
ty_python_learning/day02_flow_controls/p03_functions.py
ty_python_learning/day02_flow_controls/p04_lambdas.py
ty_python_learning/day03_objects/__init__.py
ty_python_learning/day03_objects/p01_objects.py
ty_python_learning/day03_objects/p02_extends.py
ty_python_learning/day04_exceptions/__init__.py
ty_python_learning/day04_exceptions/p01_exceptions.py
ty_python_learning/day04_exceptions/p02_self_define_exceptions.py
ty_python_learning/utils/__init__.py
ty_python_learning/utils/logger.py
ty_python_learning/utils/regs.py
ty_python_learning-0.0.2.dist-info/LICENSE
ty_python_learning-0.0.2.dist-info/METADATA
ty_python_learning-0.0.2.dist-info/WHEEL
ty_python_learning-0.0.2.dist-info/top_level.txt
ty_python_learning-0.0.2.dist-info/RECORD
